paramdiffusion/__init__.py
paramdiffusion/_utils/__init__.py
paramdiffusion/_utils/matrix_utils.py
paramdiffusion/_utils/test_utils.py
paramdiffusion/module_wrappers/__init__.py
paramdiffusion/module_wrappers/jax_wrapper.py
paramdiffusion/module_wrappers/pytorch_wrapper.py
paramdiffusion/sde/__init__.py
paramdiffusion/sde/paramsymbolic_mean_cov.py
paramdiffusion-0.0.8.dist-info/METADATA
paramdiffusion-0.0.8.dist-info/WHEEL
paramdiffusion-0.0.8.dist-info/top_level.txt
paramdiffusion-0.0.8.dist-info/RECORD
